<annotation><filename>236.jpg</filename><folder>biking_1</folder><source><sourceImage>Biking_1</sourceImage><sourceAnnotation>LabelMe Webtool</sourceAnnotation></source><object><name>Stop sign</name><deleted>0</deleted><verified>0</verified><parts><hasparts></hasparts><ispartof></ispartof></parts><date>28-Feb-2015 06:46:23</date><id>0</id><polygon><username>anonymous</username><pt><x>647</x><y>101</y></pt><pt><x>641</x><y>108</y></pt><pt><x>642</x><y>117</y></pt><pt><x>649</x><y>120</y></pt><pt><x>655</x><y>118</y></pt><pt><x>659</x><y>115</y></pt><pt><x>659</x><y>105</y></pt></polygon></object><object><name>Pedestrain Xing</name><deleted>0</deleted><verified>0</verified><parts><hasparts></hasparts><ispartof></ispartof></parts><date>28-Feb-2015 06:46:29</date><id>1</id><polygon><username>anonymous</username><pt><x>813</x><y>43</y></pt><pt><x>787</x><y>72</y></pt><pt><x>815</x><y>95</y></pt><pt><x>841</x><y>71</y></pt></polygon></object><imagesize><nrows>720</nrows><ncols>1280</ncols></imagesize></annotation>